Metadata-Version: 1.1
Name: tsincluder
Version: 0.1.1
Summary: Text Script Inclusions Manager generate contents from any text file based on shell instructions
Home-page: https://github.com/FabienArcellier/tsincluder
Author: Fabien Arcellier
Author-email: fabien.arcellier@gmail.com
License: Mozilla Public License, v. 2.0
Platform: UNKNOWN
Classifier: Development Status :: 4 - Beta
Classifier: Intended Audience :: Developers
Classifier: Intended Audience :: System Administrators
Classifier: License :: OSI Approved :: Mozilla Public License 2.0 (MPL 2.0)
Classifier: Topic :: Software Development :: Build Tools
Classifier: Topic :: Text Processing :: Markup
